odoo10_addon_shopinvader-10.0.2.22.0-py3.8-nspkg.pth
odoo/addons/shopinvader/README.rst
odoo/addons/shopinvader/__init__.py
odoo/addons/shopinvader/__manifest__.py
odoo/addons/shopinvader/shopinvader_response.py
odoo/addons/shopinvader/components/__init__.py
odoo/addons/shopinvader/components/product_product_event_listener.py
odoo/addons/shopinvader/controllers/__init__.py
odoo/addons/shopinvader/controllers/main.py
odoo/addons/shopinvader/data/cart_step.xml
odoo/addons/shopinvader/data/ir_cron.xml
odoo/addons/shopinvader/data/ir_export_category.xml
odoo/addons/shopinvader/data/ir_export_product.xml
odoo/addons/shopinvader/data/res_partner.xml
odoo/addons/shopinvader/demo/account_demo.xml
odoo/addons/shopinvader/demo/backend_demo.xml
odoo/addons/shopinvader/demo/email_demo.xml
odoo/addons/shopinvader/demo/notification_demo.xml
odoo/addons/shopinvader/demo/partner_demo.xml
odoo/addons/shopinvader/demo/pricelist_demo.xml
odoo/addons/shopinvader/demo/product_attribute_value_demo.xml
odoo/addons/shopinvader/demo/product_category_demo.xml
odoo/addons/shopinvader/demo/product_filter_demo.xml
odoo/addons/shopinvader/demo/product_product_demo.xml
odoo/addons/shopinvader/demo/res_company.xml
odoo/addons/shopinvader/demo/sale_demo.xml
odoo/addons/shopinvader/i18n/fr.po
odoo/addons/shopinvader/i18n/shopinvader.pot
odoo/addons/shopinvader/migrations/10.0.2.0.0/pre-migrate.py
odoo/addons/shopinvader/migrations/10.0.2.0.2/post-migrate.py
odoo/addons/shopinvader/migrations/10.0.2.0.3/post-migrate.py
odoo/addons/shopinvader/migrations/10.0.2.0.3/pre-migrate.py
odoo/addons/shopinvader/migrations/10.0.2.0.4/post-migrate.py
odoo/addons/shopinvader/migrations/10.0.2.0.4/pre-migrate.py
odoo/addons/shopinvader/migrations/10.0.2.7.1/post-migrate.py
odoo/addons/shopinvader/models/__init__.py
odoo/addons/shopinvader/models/account_invoice.py
odoo/addons/shopinvader/models/product_category.py
odoo/addons/shopinvader/models/product_filter.py
odoo/addons/shopinvader/models/product_product.py
odoo10_addon_shopinvader-10.0.2.22.0.dist-info/METADATA
odoo10_addon_shopinvader-10.0.2.22.0.dist-info/WHEEL
odoo10_addon_shopinvader-10.0.2.22.0.dist-info/namespace_packages.txt
odoo10_addon_shopinvader-10.0.2.22.0.dist-info/top_level.txt
odoo10_addon_shopinvader-10.0.2.22.0.dist-info/RECORD
