Metadata-Version: 2.1
Name: odoo10-addon-shopinvader
Version: 10.0.2.22.0
Summary: Shopinvader
Home-page: https://github.com/shopinvader/odoo-shopinvader
Author: Akretion
License: AGPL-3
Platform: UNKNOWN
Classifier: Programming Language :: Python
Classifier: Framework :: Odoo
Classifier: License :: OSI Approved :: GNU Affero General Public License v3
Requires-Python: ~=2.7
Requires-Dist: Cerberus (>=1.3.2)
Requires-Dist: odoo10-addon-auth-api-key
Requires-Dist: odoo10-addon-base-jsonify
Requires-Dist: odoo10-addon-base-rest
Requires-Dist: odoo10-addon-base-sparse-field-list-support
Requires-Dist: odoo10-addon-base-suspend-security
Requires-Dist: odoo10-addon-base-url
Requires-Dist: odoo10-addon-component-event
Requires-Dist: odoo10-addon-onchange-helper
Requires-Dist: odoo10-addon-queue-job
Requires-Dist: odoo10-addon-sale-discount-display-amount
Requires-Dist: odoo10-addon-sale-order-price-recalculation
Requires-Dist: odoo (<10.1dev,>=10.0)
Requires-Dist: openupgradelib
Requires-Dist: unidecode
